phitigra/__init__.py
phitigra/graph_editor.py
phitigra-0.2.6.dist-info/LICENSE
phitigra-0.2.6.dist-info/METADATA
phitigra-0.2.6.dist-info/WHEEL
phitigra-0.2.6.dist-info/top_level.txt
phitigra-0.2.6.dist-info/RECORD
