Metadata-Version: 2.1
Name: phitigra
Version: 0.2.6
Summary: A graph editor for SageMath/Jupyter
Home-page: https://github.com/jfraymond/phitigra
Author: Jean-Florent Raymond
Author-email: j-florent.raymond@uca.fr
Project-URL: Bug Tracker, https://github.com/jfraymond/phitigra/issues
Classifier: Programming Language :: Python :: 3
Classifier: License :: OSI Approved :: MIT License
Classifier: Operating System :: OS Independent
Classifier: Development Status :: 5 - Production/Stable
Classifier: Intended Audience :: Science/Research
Classifier: Topic :: Scientific/Engineering :: Mathematics
Requires-Python: >=3.6
License-File: LICENSE
Requires-Dist: ipycanvas (>=0.12.0)
Requires-Dist: ipywidgets
